
{
	"EXTRACT_NEWS": {"TIME":"weekly|monday|7:43:00",
					"SPORTS": ["TENNIS", "BASKETBALL","AMERICAN_SPORTS", 
							  "HOCKEY"],
					"MAX_OLDER_DATE_ALLOWED":31
					},
	"CREATE_LEAGUES": {"TIME":"weekly|tuesday|12:35:00",
						"SPORTS": ["HOCKEY", "BASKETBALL"]},

	"CREATE_TEAMS": {"TIME":"weekly|tuesday|12:50:00", 
					"SPORTS": ["HOCKEY", "BASKETBALL"]},

	"GET_RESULTS": {"TIME":"weekly|monday|14:16:30", 
					"SPORTS": ["FOOTBALL", "BASKETBALL", "HOCKEY", "AM._FOOTBALL",
					  "BASEBALL","BOXING", "VOLLEYBALL"]},

	"GET_FIXTURES": {"TIME":"weekly|monday|17:00:00",
					"SPORTS": ["FOOTBALL", "BASKETBALL", "HOCKEY", "AM._FOOTBALL",
					  "BASEBALL","BOXING", "VOLLEYBALL"]},
	"GET_PLAYERS": {"TIME":"weekly|wednesday|18:40:00",
					"SPORTS": ["HOCKEY"]},
	"LIVE_SECTION": {"TIME":"seconds|60",
					"SPORTS": ["FOOTBALL", "TENNIS", "BASKETBALL", "HOCKEY", "GOLF", "AM._FOOTBALL",
					  "BASEBALL","BOXING", "MOTORSPORT", "VOLLEYBALL"]},
	"EXAMPLE": {"TIME":"seconds|90|14:15:00",
					"SPORTS": ["FOOTBALL", "TENNIS", "BASKETBALL", "HOCKEY", "GOLF", "AM._FOOTBALL",
					  "BASEBALL","BOXING", "MOTORSPORT", "VOLLEYBALL"]}

}


