{
    "0": {
        "match_id": "cspa05995",
        "match_date": "08.10. 13:20",
        "start_time": "",
        "end_time": "",
        "name": "Mountfield HK-Pardubice",
        "home": "Mountfield HK",
        "visitor": "Pardubice",
        "home_result": "2",
        "visitor_result": "4",
        "link_details": "https://www.flashscore.com/match/v7PYLqnn/#/match-summary/match-summary",
        "place": ""
    },
    "1": {
        "match_id": "oznp01762",
        "match_date": "08.10. 11:30",
        "start_time": "",
        "end_time": "",
        "name": "Litvinov-Ceske Budejovice",
        "home": "Litvinov",
        "visitor": "Ceske Budejovice",
        "home_result": "4",
        "visitor_result": "3",
        "link_details": "https://www.flashscore.com/match/4hZN32WH/#/match-summary/match-summary",
        "place": ""
    },
    "2": {
        "match_id": "qjpq90705",
        "match_date": "08.10. 11:00\nAOT",
        "start_time": "",
        "end_time": "",
        "name": "Kometa Brno-Olomouc",
        "home": "Kometa Brno",
        "visitor": "Olomouc",
        "home_result": "3",
        "visitor_result": "2",
        "link_details": "https://www.flashscore.com/match/x6XV1t1U/#/match-summary/match-summary",
        "place": ""
    },
    "3": {
        "match_id": "txqp05379",
        "match_date": "08.10. 11:00",
        "start_time": "",
        "end_time": "",
        "name": "Trinec-Karlovy Vary",
        "home": "Trinec",
        "visitor": "Karlovy Vary",
        "home_result": "5",
        "visitor_result": "1",
        "link_details": "https://www.flashscore.com/match/bFYR2MoO/#/match-summary/match-summary",
        "place": ""
    },
    "4": {
        "match_id": "obkm08558",
        "match_date": "08.10. 10:00",
        "start_time": "",
        "end_time": "",
        "name": "Mlada Boleslav-Kladno",
        "home": "Mlada Boleslav",
        "visitor": "Kladno",
        "home_result": "3",
        "visitor_result": "4",
        "link_details": "https://www.flashscore.com/match/jkVJ4rHB/#/match-summary/match-summary",
        "place": ""
    },
    "5": {
        "match_id": "smtb92107",
        "match_date": "08.10. 10:00",
        "start_time": "",
        "end_time": "",
        "name": "Sparta Prague-Liberec",
        "home": "Sparta Prague",
        "visitor": "Liberec",
        "home_result": "1",
        "visitor_result": "4",
        "link_details": "https://www.flashscore.com/match/0GQUMPWu/#/match-summary/match-summary",
        "place": ""
    },
    "6": {
        "match_id": "lmav90959",
        "match_date": "08.10. 09:00",
        "start_time": "",
        "end_time": "",
        "name": "Plzen-Vitkovice",
        "home": "Plzen",
        "visitor": "Vitkovice",
        "home_result": "1",
        "visitor_result": "0",
        "link_details": "https://www.flashscore.com/match/8QuF5O15/#/match-summary/match-summary",
        "place": ""
    }
}