{
    "Eisbaren Berlin": {
        "team_id": "ccps92811",
        "team_url": "https://www.flashscore.com/team/eisbaren-berlin/vwLXr6U8/"
    },
    "Bremerhaven": {
        "team_id": "phnk99146",
        "team_url": "https://www.flashscore.com/team/pinguins-bremerhaven/vRV0SS63/"
    },
    "Straubing Tigers": {
        "team_id": "rxig93420",
        "team_url": "https://www.flashscore.com/team/straubing-tigers/4rgakDjm/"
    },
    "Munchen": {
        "team_id": "jorl92015",
        "team_url": "https://www.flashscore.com/team/munchen/dOHrLrqd/"
    },
    "Schwenninger": {
        "team_id": "dlii98920",
        "team_url": "https://www.flashscore.com/team/schwenninger/x8GmLQb2/"
    },
    "Grizzly Wolfsburg": {
        "team_id": "filr07723",
        "team_url": "https://www.flashscore.com/team/grizzly-wolfsburg/pjtzLXj0/"
    },
    "Kolner": {
        "team_id": "lspt08590",
        "team_url": "https://www.flashscore.com/team/kolner-haie/va2irFDJ/"
    },
    "Adler Mannheim": {
        "team_id": "iffz94773",
        "team_url": "https://www.flashscore.com/team/adler-mannheim/0jhpSN72/"
    },
    "ERC Ingolstadt": {
        "team_id": "eaad90326",
        "team_url": "https://www.flashscore.com/team/erc-ingolstadt/OzEsAZ6s/"
    },
    "Nurnberg Ice Tigers": {
        "team_id": "rwds90511",
        "team_url": "https://www.flashscore.com/team/nurnberg-ice-tigers/Qifejgys/"
    },
    "Dusseldorf": {
        "team_id": "vkga91585",
        "team_url": "https://www.flashscore.com/team/dusseldorf/nBjER1xF/"
    },
    "Frankfurt Lowen": {
        "team_id": "ccnn09896",
        "team_url": "https://www.flashscore.com/team/frankfurt-lowen/6a3n9gMm/"
    },
    "Iserlohn Roosters": {
        "team_id": "jjkc91407",
        "team_url": "https://www.flashscore.com/team/iserlohn-roosters/Mwj1JVzJ/"
    },
    "Augsburger Panther": {
        "team_id": "ujjn99968",
        "team_url": "https://www.flashscore.com/team/augsburger-panther/vsilRsN8/"
    }
}